drcell/DrCELLBrokehApplication.py
drcell/DrCELLQWindow.py
drcell/__init__.py
drcell/dimensionalReduction/CEBRADRObject.py
drcell/dimensionalReduction/CustomDimensionalReductionObjectExample.py
drcell/dimensionalReduction/DimensionalReductionObject.py
drcell/dimensionalReduction/PHATEDRObject.py
drcell/dimensionalReduction/TSNEDRObject.py
drcell/dimensionalReduction/UMAPDRObject.py
drcell/dimensionalReduction/__init__.py
drcell/scripts/__init__.py
drcell/scripts/convertExampleDataset.py
drcell/scripts/convertLegacyMatFiles.py
drcell/scripts/startApplication.py
drcell/scripts/startBokehServer.py
drcell/scripts/startImageServer.py
drcell/server/DrCELLBokehServer.py
drcell/server/ImageServer.py
drcell/server/__init__.py
drcell/util/__init__.py
drcell/util/drCELLFileUtil.py
drcell/util/generalUtil.py
drcell/util/plottingUtil.py
drcell-0.0.1rc2.dist-info/METADATA
drcell-0.0.1rc2.dist-info/WHEEL
drcell-0.0.1rc2.dist-info/entry_points.txt
drcell-0.0.1rc2.dist-info/top_level.txt
drcell-0.0.1rc2.dist-info/RECORD
