Metadata-Version: 2.1
Name: drcell
Version: 0.0.1rc2
Summary: GUI to generate, cluster and optimize dimensionality reduction output
Home-page: https://github.com/lucakoe/DrCELL
Author: Luca K.
Author-email: pypi@use.startmail.com
Classifier: Programming Language :: Python :: 3
Classifier: License :: OSI Approved :: MIT License
Classifier: Operating System :: Microsoft :: Windows
Requires-Python: >=3.6
Requires-Dist: bleach==6.1.0
Requires-Dist: blosc2==2.5.1
Requires-Dist: bokeh==3.3.4
Requires-Dist: certifi==2024.7.4
Requires-Dist: charset-normalizer==3.3.2
Requires-Dist: click==8.1.7
Requires-Dist: cloudpickle==3.0.0
Requires-Dist: colorama==0.4.6
Requires-Dist: colorcet==3.1.0
Requires-Dist: contourpy==1.2.1
Requires-Dist: cycler==0.12.1
Requires-Dist: cython==0.29.37
Requires-Dist: dask[array,dataframe]==2024.8.0
Requires-Dist: dask-expr==1.1.10
Requires-Dist: datashader==0.16.3
Requires-Dist: decorator==5.1.1
Requires-Dist: deprecated==1.2.14
Requires-Dist: filelock==3.15.4
Requires-Dist: fonttools==4.53.1
Requires-Dist: fsspec==2024.6.1
Requires-Dist: future==1.0.0
Requires-Dist: graphtools==1.5.3
Requires-Dist: h5py==3.11.0
Requires-Dist: hdbscan==0.8.33
Requires-Dist: holoviews==1.19.1
Requires-Dist: idna==3.7
Requires-Dist: imageio==2.35.0
Requires-Dist: importlib-metadata==8.2.0
Requires-Dist: importlib-resources==6.4.3
Requires-Dist: jinja2==3.1.4
Requires-Dist: joblib==1.4.2
Requires-Dist: kiwisolver==1.4.5
Requires-Dist: lazy-loader==0.4
Requires-Dist: linkify-it-py==2.0.3
Requires-Dist: llvmlite==0.43.0
Requires-Dist: locket==1.0.0
Requires-Dist: markdown==3.7
Requires-Dist: markdown-it-py==3.0.0
Requires-Dist: markupsafe==2.1.5
Requires-Dist: matplotlib==3.9.2
Requires-Dist: mdit-py-plugins==0.4.1
Requires-Dist: mdurl==0.1.2
Requires-Dist: mpmath==1.3.0
Requires-Dist: msgpack==1.0.8
Requires-Dist: multipledispatch==1.0.0
Requires-Dist: ndindex==1.8
Requires-Dist: networkx==3.2.1
Requires-Dist: numba==0.60.0
Requires-Dist: numexpr==2.10.1
Requires-Dist: numpy==1.26.4
Requires-Dist: packaging==24.1
Requires-Dist: pandas==2.0.3
Requires-Dist: panel==1.3.8
Requires-Dist: param==2.1.1
Requires-Dist: partd==1.4.2
Requires-Dist: phate==1.0.11
Requires-Dist: pillow==10.4.0
Requires-Dist: py-cpuinfo==9.0.0
Requires-Dist: pyarrow==17.0.0
Requires-Dist: pyct==0.5.0
Requires-Dist: pygsp==0.5.1
Requires-Dist: pynndescent==0.5.13
Requires-Dist: pyparsing==3.1.2
Requires-Dist: pyqt5==5.15.11
Requires-Dist: pyqt5-qt5==5.15.2
Requires-Dist: pyqt5-sip==12.15.0
Requires-Dist: pyqtwebengine==5.15.7
Requires-Dist: pyqtwebengine-qt5==5.15.2
Requires-Dist: python-dateutil==2.9.0.post0
Requires-Dist: pytz==2024.1
Requires-Dist: pyviz-comms==3.0.3
Requires-Dist: pyyaml==6.0.2
Requires-Dist: requests==2.32.3
Requires-Dist: s-gd2==1.8.1
Requires-Dist: scikit-image==0.24.0
Requires-Dist: scikit-learn==1.5.1
Requires-Dist: scipy==1.13.1
Requires-Dist: scprep==1.2.3
Requires-Dist: seaborn==0.13.2
Requires-Dist: six==1.16.0
Requires-Dist: sympy==1.13.2
Requires-Dist: tables==3.9.2
Requires-Dist: tasklogger==1.2.0
Requires-Dist: threadpoolctl==3.5.0
Requires-Dist: tifffile==2024.8.10
Requires-Dist: toolz==0.12.1
Requires-Dist: torch==2.4.0
Requires-Dist: tornado==6.4.1
Requires-Dist: tqdm==4.66.5
Requires-Dist: typing-extensions==4.12.2
Requires-Dist: tzdata==2024.1
Requires-Dist: uc-micro-py==1.0.3
Requires-Dist: umap-learn[plot]==0.5.6
Requires-Dist: urllib3==2.2.2
Requires-Dist: webencodings==0.5.1
Requires-Dist: wrapt==1.16.0
Requires-Dist: xarray==2024.7.0
Requires-Dist: xyzservices==2024.6.0
Requires-Dist: zipp==3.20.0
